{
	"commentStamp" : "JhonnathamSalgado 11/15/2014 19:18",
	"super" : "PMModelObject",
	"category" : "ProcessModel-Core",
	"classinstvars" : [ ],
	"pools" : [ ],
	"classvars" : [ ],
	"instvars" : [
		"artifactOutputs",
		"artifactMandatoryInputs",
		"roles",
		"roleIds",
		"desviationToMeanOutputArtifacts",
		"desviationToMeanInputArtifacts",
		"baseTask",
		"variabilityType",
		"visibility",
		"resolvedVariability",
		"contributor",
		"use",
		"predecessors",
		"taskDescriptors"
	],
	"name" : "PMTask",
	"type" : "normal"
}